pythorhead/__init__.py
pythorhead/admin.py
pythorhead/auth.py
pythorhead/class_methods.py
pythorhead/comment.py
pythorhead/community.py
pythorhead/emoji.py
pythorhead/image.py
pythorhead/lemmy.py
pythorhead/mention.py
pythorhead/modlog.py
pythorhead/post.py
pythorhead/private_message.py
pythorhead/requestor.py
pythorhead/site.py
pythorhead/user.py
pythorhead/utils.py
pythorhead/classes/__init__.py
pythorhead/classes/admin.py
pythorhead/classes/base.py
pythorhead/classes/user.py
pythorhead/types/__init__.py
pythorhead/types/feature.py
pythorhead/types/language.py
pythorhead/types/listing.py
pythorhead/types/modlog.py
pythorhead/types/search.py
pythorhead/types/sort.py
pythorhead-0.34.3.dist-info/licenses/CHANGELOG.md
pythorhead-0.34.3.dist-info/licenses/LICENSE
pythorhead-0.34.3.dist-info/METADATA
pythorhead-0.34.3.dist-info/WHEEL
pythorhead-0.34.3.dist-info/top_level.txt
pythorhead-0.34.3.dist-info/RECORD
