Metadata-Version: 2.4
Name: pythorhead
Version: 0.34.3
Summary: A python library for interacting with Lemmy API
Author-email: db0 <mail@dbzer0.com>
License:                     GNU AFFERO GENERAL PUBLIC LICENSE
Project-URL: Homepage, https://github.com/db0/pythorhead
Classifier: Programming Language :: Python :: 3
Classifier: License :: OSI Approved :: GNU Affero General Public License v3
Classifier: Operating System :: OS Independent
Classifier: Development Status :: 2 - Pre-Alpha
Requires-Python: >=3.10
License-File: LICENSE
License-File: CHANGELOG.md
Requires-Dist: requests<3.0.0,>=2.31.0
Requires-Dist: semver>=3.0.2
Requires-Dist: pillow>=10.2.0
Requires-Dist: python-dateutil>=2.9.0
Requires-Dist: loguru>=0.7.3
Dynamic: license-file
